<annotation>
	<folder>arranged</folder>
	<filename>011_L0301220338_1.jpg</filename>
	<path>/home/ntnnhi/build_data/arranged/011_L0301220338_1.jpg</path>
	<source>
		<database>Unknown</database>
	</source>
	<size>
		<width>800</width>
		<height>1975</height>
		<depth>3</depth>
	</size>
	<segmented>0</segmented>
	<object>
		<name>store</name>
		<pose>Unspecified</pose>
		<truncated>0</truncated>
		<difficult>0</difficult>
		<bndbox>
			<xmin>71</xmin>
			<ymin>22</ymin>
			<xmax>694</xmax>
			<ymax>601</ymax>
		</bndbox>
	</object>
	<object>
		<name>total</name>
		<pose>Unspecified</pose>
		<truncated>0</truncated>
		<difficult>0</difficult>
		<bndbox>
			<xmin>567</xmin>
			<ymin>869</ymin>
			<xmax>771</xmax>
			<ymax>936</ymax>
		</bndbox>
	</object>
	<object>
		<name>id</name>
		<pose>Unspecified</pose>
		<truncated>0</truncated>
		<difficult>0</difficult>
		<bndbox>
			<xmin>87</xmin>
			<ymin>1481</ymin>
			<xmax>438</xmax>
			<ymax>1538</ymax>
		</bndbox>
	</object>
	<object>
		<name>date</name>
		<pose>Unspecified</pose>
		<truncated>0</truncated>
		<difficult>0</difficult>
		<bndbox>
			<xmin>55</xmin>
			<ymin>632</ymin>
			<xmax>236</xmax>
			<ymax>693</ymax>
		</bndbox>
	</object>
</annotation>
